terragrunt_source/__init__.py
terragrunt_source-0.1.0a3.dist-info/METADATA
terragrunt_source-0.1.0a3.dist-info/RECORD
terragrunt_source-0.1.0a3.dist-info/WHEEL
terragrunt_source-0.1.0a3.dist-info/entry_points.txt
terragrunt_source-0.1.0a3.dist-info/top_level.txt
tests/__init__.py
tests/test_terragrunt_source.py
