Metadata-Version: 2.1
Name: terragrunt-source
Version: 0.1.0a3
Summary: A Terragrunt rapid development tool to simplify overriding the source parameter in a terraform.tfvars file.
Home-page: https://github.com/ddriddle/terragrunt-source
Author: David D. Riddle
Author-email: ddriddle@illinois.edu
License: UNKNOWN
Project-URL: Bug Reports, https://github.com/ddriddle/terragrunt-source/issues
Project-URL: Source, https://github.com/ddriddle/terragrunt-source
Keywords: terragrunt terraform source
Platform: UNKNOWN
Classifier: Development Status :: 3 - Alpha
Classifier: Environment :: Console
Classifier: Intended Audience :: Developers
Classifier: License :: OSI Approved :: MIT License
Classifier: Natural Language :: English
Classifier: Programming Language :: Python :: 2.6
Classifier: Programming Language :: Python :: 2.7
Classifier: Programming Language :: Python :: 3
Classifier: Programming Language :: Python :: 3.1
Classifier: Programming Language :: Python :: 3.2
Classifier: Programming Language :: Python :: 3.3
Classifier: Programming Language :: Python :: 3.4
Classifier: Programming Language :: Python :: 3.5
Classifier: Programming Language :: Python :: 3.6
Requires-Python: >=2.6
Requires-Dist: pyhcl
Requires-Dist: future; python_version < "3"
